{
  "type": "excalidraw",
  "version": 2,
  "source": "local",
  "elements": [
    {
      "id": "rect1",
      "type": "rectangle",
      "x": 100,
      "y": 100,
      "width": 200,
      "height": 100,
      "angle": 0,
      "strokeColor": "#000000",
      "backgroundColor": "transparent",
      "fillStyle": "hachure",
      "strokeWidth": 1,
      "strokeStyle": "solid",
      "roughness": 1,
      "opacity": 100,
      "groupIds": [],
      "seed": 1,
      "version": 1,
      "versionNonce": 1,
      "isDeleted": false,
      "boundElements": null,
      "updated": 1,
      "link": null,
      "locked": false
    },
    {
      "id": "text1",
      "type": "text",
      "x": 120,
      "y": 130,
      "width": 160,
      "height": 30,
      "angle": 0,
      "strokeColor": "#000000",
      "backgroundColor": "transparent",
      "fillStyle": "hachure",
      "strokeWidth": 1,
      "strokeStyle": "solid",
      "roughness": 1,
      "opacity": 100,
      "groupIds": [],
      "seed": 2,
      "version": 1,
      "versionNonce": 1,
      "isDeleted": false,
      "boundElements": null,
      "updated": 1,
      "link": null,
      "locked": false,
      "text": "こんにちは Excalidraw",
      "fontSize": 20,
      "fontFamily": 1,
      "textAlign": "center",
      "verticalAlign": "middle",
      "baseline": 18,
      "containerId": null,
      "originalText": "こんにちは Excalidraw",
      "lineHeight": 1.2
    }
  ],
  "appState": {
    "viewBackgroundColor": "#ffffff"
  },
  "files": {}
}